{"Folder":"00020_CRANWheatData","Done":"NA","Person_working":"Harish","DOI":"NA","Publication_link":"NA","Title":"Genomic Analysis and Prediction within a US Public Collaborative Winter Wheat Regional Testing Nursery","Abstract":"NA","Scientific_Name":"Triticum aestivum","Common_Name":"Wheat","Sharing_Link":"https://search.r-project.org/CRAN/refmans/BGLR/html/wheat.html","...11":"NA","Requires_Authorization":false,"Phenotype":true,"Map":false,"Pedigree":false,"N_Geno":599,"N_markers":1279,"Download_Instructions":"NA"}
